receptor_utils/__init__.py
receptor_utils/aux_formats.py
receptor_utils/check_aux.py
receptor_utils/check_fastas.py
receptor_utils/check_ndm.py
receptor_utils/novel_allele_name.py
receptor_utils/number_v.py
receptor_utils/sequence_alignment.py
receptor_utils/simple_bio_seq.py
receptor_utils-0.0.63.dist-info/licenses/LICENSE
scripts/__init__.py
scripts/annotate_j.py
scripts/at_coords.py
scripts/create_alignment.py
scripts/download_germline_set.py
scripts/extract_refs.py
scripts/fix_macaque_gaps.py
scripts/gap_inferred.py
scripts/identical_seqs.py
scripts/make_igblast_ndm.py
scripts/merge_fasta.py
scripts/name_allele.py
scripts/reverse_complement.py
receptor_utils-0.0.63.dist-info/METADATA
receptor_utils-0.0.63.dist-info/WHEEL
receptor_utils-0.0.63.dist-info/entry_points.txt
receptor_utils-0.0.63.dist-info/top_level.txt
receptor_utils-0.0.63.dist-info/RECORD
