Metadata-Version: 2.4
Name: receptor_utils
Version: 0.0.63
Summary: Some tools I find useful for working with Ig receptor sequences
Home-page: https://github.com/williamdlees/receptor_utils
Author: William Lees
Author-email: william@lees.org.uk
License: EUPL-1.2
Project-URL: Bug Tracker, https://github.com/williamdlees/receptor_utils/issues
Classifier: Programming Language :: Python :: 3
Classifier: Operating System :: OS Independent
Requires-Python: >=3.9
License-File: LICENSE
Requires-Dist: biopython>=1.81
Requires-Dist: requests>=2.28
Dynamic: license-file
